DependencyNeedle/__init__.py
DependencyNeedle/constants/__init__.py
DependencyNeedle/constants/constants.py
DependencyNeedle/container/__init__.py
DependencyNeedle/container/container.py
DependencyNeedle/dependency_strategy/__init__.py
DependencyNeedle/dependency_strategy/dependency_strategy_interface.py
DependencyNeedle/dependency_strategy/scoped_dependency_strategy.py
DependencyNeedle/dependency_strategy/singleton_dependency_strategy.py
DependencyNeedle/dependency_strategy/transient_dependency_strategy.py
DependencyNeedle/example/__init__.py
DependencyNeedle/example/example.py
DependencyNeedle/lifetime_enums/__init__.py
DependencyNeedle/lifetime_enums/lifetime_enums.py
DependencyNeedle-0.0.1.dist-info/METADATA
DependencyNeedle-0.0.1.dist-info/WHEEL
DependencyNeedle-0.0.1.dist-info/top_level.txt
DependencyNeedle-0.0.1.dist-info/RECORD
